{
  "VoidT1": [
    "SolNode23",
    "SolNode66",
    "SolNode45",
    "SolNode41",
    "SolNode59",
    "SolNode39",
    "SolNode75",
    "SolNode113",
    "SolNode85",
    "SolNode58",
    "SolNode101",
    "SolNode109",
    "SolNode26",
    "SolNode15",
    "SolNode61",
    "SolNode123",
    "SolNode16",
    "SolNode79",
    "SolNode2",
    "SolNode22",
    "SolNode68",
    "SolNode89",
    "SolNode11",
    "SolNode46",
    "SolNode36",
    "SolNode27",
    "SolNode14",
    "SolNode106",
    "SolNode30",
    "SolNode107",
    "SolNode63",
    "SolNode128"
  ],
  "VoidT2": [
    "SolNode141",
    "SolNode149",
    "SolNode10",
    "SolNode93",
    "SettlementNode11",
    "SolNode137",
    "SolNode132",
    "SolNode73",
    "SolNode82",
    "SolNode25",
    "SolNode88",
    "SolNode126",
    "SolNode135",
    "SolNode74",
    "SettlementNode15",
    "SolNode147",
    "SolNode67",
    "SolNode20",
    "SolNode42",
    "SolNode18",
    "SolNode31",
    "SolNode139",
    "SettlementNode12",
    "SolNode100",
    "SolNode140",
    "SolNode70",
    "SettlementNode1",
    "SettlementNode14",
    "SolNode50",
    "SettlementNode2",
    "SolNode146",
    "SettlementNode3",
    "SolNode97",
    "SolNode125",
    "SolNode19",
    "SolNode121",
    "SolNode96",
    "SolNode131"
  ],
  "VoidT3": [
    "SolNode62",
    "SolNode17",
    "SolNode403",
    "SolNode6",
    "SolNode118",
    "SolNode211",
    "SolNode217",
    "SolNode401",
    "SolNode64",
    "SolNode405",
    "SolNode84",
    "SolNode402",
    "SolNode408",
    "SolNode122",
    "SolNode57",
    "SolNode216",
    "SolNode205",
    "SolNode215",
    "SolNode404",
    "SolNode209",
    "SolNode406",
    "SolNode204",
    "SolNode203",
    "SolNode409",
    "SolNode400",
    "SolNode212",
    "SolNode1",
    "SolNode412",
    "SolNode49",
    "SolNode78",
    "SolNode410",
    "SolNode407",
    "SolNode220"
  ],
  "VoidT4": [
    "SolNode188",
    "SolNode403",
    "SolNode189",
    "SolNode21",
    "SolNode102",
    "SolNode171",
    "SolNode196",
    "SolNode184",
    "SolNode185",
    "SolNode76",
    "SolNode195",
    "SolNode164",
    "SolNode401",
    "SolNode405",
    "SolNode56",
    "SolNode402",
    "SolNode408",
    "SolNode4",
    "SolNode181",
    "SolNode406",
    "SolNode162",
    "SolNode72",
    "SolNode407",
    "SolNode177",
    "SolNode404",
    "SolNode400",
    "SolNode409",
    "SolNode43",
    "SolNode166",
    "SolNode172",
    "SolNode412",
    "SolNode187",
    "SolNode38",
    "SolNode175",
    "SolNode81",
    "SolNode48",
    "SolNode410",
    "SolNode153",
    "SolNode173"
  ],
  "VoidT5": ["SolNode747", "SolNode743", "SolNode742", "SolNode744", "SolNode745", "SolNode748", "SolNode746", "SolNode741"],
  "VoidT6": ["SolNode717", "SolNode309", "SolNode718", "SolNode232", "SolNode230", "SolNode310"]
}
